[
  {
    "id": "1771875438647",
    "name": "pp",
    "phone": "8080980998",
    "area": "Kothrud",
    "services": "Full Home 360°, Modular Kitchens, Living Room Setup, Bedroom Oasis",
    "status": "Contacted",
    "timestamp": "2026-02-23T19:37:18.647Z"
  },
  {
    "id": "1771878962815",
    "name": "anav",
    "phone": "8080531468",
    "area": "Viman Nagar",
    "services": "The Solar Package (1BHK), The Supernova Package (2BHK/3BHK), The Galaxy Estate (Villas/Bungalows), Nebula Lighting Design, Cosmic Home Office, Astro-Vastu Consultation, Stardust Wall Treatments, Celestial Upholstery, The 'Final Frontier' Deep Cleaning, Full Turnkey Projects, Smart Home Integration, Civil & Structural Changes, Landscape & Balcony Gardening, Commercial Space Design",
    "status": "Contacted",
    "timestamp": "2026-02-23T20:36:02.815Z"
  },
  {
    "id": "1771998984667",
    "name": "anav testing",
    "phone": "8080763573",
    "area": "Viman Nagar",
    "services": "Full Turnkey Projects, Smart Home Integration, Civil & Structural Changes",
    "status": "Contacted",
    "timestamp": "2026-02-25T05:56:24.667Z"
  }
]